lightcat/__init__.py
lightcat/data/__init__.py
lightcat/utils/__init__.py
lightcat/utils/factory.py
lightcat-0.0.0a1.dist-info/LICENSE
lightcat-0.0.0a1.dist-info/METADATA
lightcat-0.0.0a1.dist-info/WHEEL
lightcat-0.0.0a1.dist-info/RECORD
