Metadata-Version: 2.1
Name: lightcat
Version: 0.0.0a1
Summary: 
Home-page: https://github.com/durandtibo/lightcat
License: BSD-3-Clause
Keywords: equality,complex/nested objects
Author: Thibaut Durand
Author-email: durand.tibo+gh@gmail.com
Requires-Python: >=3.9,<4.0
Classifier: Development Status :: 2 - Pre-Alpha
Classifier: Intended Audience :: Developers
Classifier: Intended Audience :: Science/Research
Classifier: License :: OSI Approved :: BSD License
Classifier: Operating System :: POSIX :: Linux
Classifier: Programming Language :: Python :: 3
Classifier: Programming Language :: Python :: 3.9
Classifier: Programming Language :: Python :: 3.10
Classifier: Programming Language :: Python :: 3.11
Classifier: Topic :: Scientific/Engineering :: Artificial Intelligence
Requires-Dist: coola (>=0.0.7,<0.1)
Requires-Dist: lightning (>=2.0,<3.0)
Requires-Dist: objectory (>=0.0.2,<0.1)
Requires-Dist: torch (>=2.0,<3.0)
Project-URL: Repository, https://github.com/durandtibo/lightcat
